{
  "positions": {
    "SNDX": {
      "symbol": "SNDX",
      "shares": 588.24,
      "entry_price": 42.5,
      "current_price": 20.14,
      "market_value": 11847.06,
      "cost_basis": 25000,
      "unrealized_pnl": -13152.94,
      "unrealized_pnl_pct": -0.5261,
      "sector": "Healthcare",
      "stop_loss": 39.1,
      "catalyst": "Q3 earnings Oct 30, HIV treatment pipeline updates",
      "technical_setup": "Support at $40.50, resistance at $45.20"
    },
    "EPAM": {
      "symbol": "EPAM",
      "shares": 128.21,
      "entry_price": 195.0,
      "current_price": 95.73,
      "market_value": 12273.08,
      "cost_basis": 25000,
      "unrealized_pnl": -12726.92,
      "unrealized_pnl_pct": -0.5091,
      "sector": "Technology",
      "stop_loss": 179.4,
      "catalyst": "Q3 earnings Oct 31, digital transformation demand recovery",
      "technical_setup": "Breakout above $190, support at $185"
    },
    "STRL": {
      "symbol": "STRL",
      "shares": 78.12,
      "entry_price": 320.0,
      "current_price": 842.41,
      "market_value": 65813.28,
      "cost_basis": 25000,
      "unrealized_pnl": 40813.28,
      "unrealized_pnl_pct": 1.6325,
      "sector": "Healthcare",
      "stop_loss": 294.4,
      "catalyst": "FDA decision on liver cancer drug expected Oct 2025",
      "technical_setup": "Consolidating above $310 support, resistance at $340"
    },
    "IDCC": {
      "symbol": "IDCC",
      "shares": 185.19,
      "entry_price": 135.0,
      "current_price": 256.94,
      "market_value": 47581.48,
      "cost_basis": 25000,
      "unrealized_pnl": 22581.48,
      "unrealized_pnl_pct": 0.9033,
      "sector": "Technology",
      "stop_loss": 124.2,
      "catalyst": "5G patent licensing renewals Q4, AI chip IP monetization",
      "technical_setup": "Testing resistance at $138, strong support at $130"
    }
  },
  "benchmarks": {
    "MDY": 696.41,
    "IJH": 74.72,
    "VO": 80.93
  },
  "last_update": "2026-06-09T22:58:50.054672",
  "experiment_start": "2025-09-23",
  "cash": 0,
  "portfolio_value": 137514.9,
  "total_invested": 100000,
  "total_return": 37514.9,
  "total_return_pct": 0.3751,
  "positions_count": 4,
  "max_loss": 8000.0
}